topology_lib_ip/__init__.py
topology_lib_ip/library.py
topology_lib_ip-0.3.0.dist-info/LICENSE
topology_lib_ip-0.3.0.dist-info/METADATA
topology_lib_ip-0.3.0.dist-info/WHEEL
topology_lib_ip-0.3.0.dist-info/entry_points.txt
topology_lib_ip-0.3.0.dist-info/top_level.txt
topology_lib_ip-0.3.0.dist-info/RECORD
