Metadata-Version: 2.1
Name: topology-lib-ip
Version: 0.3.0
Summary: Linux ip command Communication Library for Topology
Home-page: https://github.com/HPENetworking/topology_lib_ip/tree/master/doc
Author: Hewlett Packard Enterprise Development LP
Author-email: hpe-networking@lists.hp.com
License: UNKNOWN
Keywords: topology_lib_ip
Platform: UNKNOWN
Classifier: Development Status :: 3 - Alpha
Classifier: Intended Audience :: Developers
Classifier: License :: OSI Approved :: Apache Software License
Classifier: Natural Language :: English
Classifier: Operating System :: POSIX :: Linux
Classifier: Programming Language :: Python :: 2
Classifier: Programming Language :: Python :: 2.7
Classifier: Programming Language :: Python :: 3
Classifier: Programming Language :: Python :: 3.4
Requires-Dist: six
Requires-Dist: ipaddress
